{
  "applications": "*",
  "changelogDate": "20230524155657",
  "dto": "no",
  "embedded": false,
  "entityTableName": "set_of",
  "fields": [
    {
      "fieldName": "title",
      "fieldType": "String"
    }
  ],
  "fluentMethods": true,
  "jpaMetamodelFiltering": false,
  "name": "SetOf",
  "pagination": "no",
  "readOnly": false,
  "relationships": [
    {
      "otherEntityField": "title",
      "otherEntityName": "fragment",
      "otherEntityRelationshipName": "setOf",
      "ownerSide": false,
      "relationshipName": "fragment",
      "relationshipType": "many-to-many"
    }
  ],
  "service": "serviceImpl"
}
